django_github_app/__init__.py
django_github_app/_sync.py
django_github_app/_typing.py
django_github_app/admin.py
django_github_app/apps.py
django_github_app/checks.py
django_github_app/conf.py
django_github_app/github.py
django_github_app/mentions.py
django_github_app/models.py
django_github_app/py.typed
django_github_app/routing.py
django_github_app/views.py
django_github_app/events/__init__.py
django_github_app/events/ahandlers.py
django_github_app/events/ainstallation.py
django_github_app/events/arepository.py
django_github_app/events/handlers.py
django_github_app/events/installation.py
django_github_app/events/repository.py
django_github_app/management/__init__.py
django_github_app/management/commands/__init__.py
django_github_app/management/commands/github.py
django_github_app/migrations/0001_initial.py
django_github_app/migrations/__init__.py
django_github_app/templates/admin/django_github_app/eventlog/change_list.html
django_github_app/templates/admin/django_github_app/eventlog/cleanup.html
django_github_app/templates/admin/django_github_app/eventlog/cleanup_confirmation.html
django_github_app/templates/admin/django_github_app/eventlog/includes/cleanup_breadcrumbs.html
django_github_app-0.9.0.dist-info/METADATA
django_github_app-0.9.0.dist-info/WHEEL
django_github_app-0.9.0.dist-info/licenses/AUTHORS.md
django_github_app-0.9.0.dist-info/licenses/LICENSE
django_github_app-0.9.0.dist-info/RECORD
