Metadata-Version: 2.4
Name: django-github-app
Version: 0.9.0
Summary: A Django toolkit for GitHub Apps with batteries included.
Project-URL: Documentation, https://github.com/joshuadavidthomas/django-github-app#README
Project-URL: Issues, https://github.com/joshuadavidthomas/django-github-app/issues
Project-URL: Source, https://github.com/joshuadavidthomas/django-github-app
Author-email: Josh Thomas <josh@joshthomas.dev>
License: MIT License
License-File: AUTHORS.md
License-File: LICENSE
Classifier: Development Status :: 4 - Beta
Classifier: Framework :: Django
Classifier: Framework :: Django :: 4.2
Classifier: Framework :: Django :: 5.1
Classifier: Framework :: Django :: 5.2
Classifier: License :: OSI Approved :: MIT License
Classifier: Operating System :: OS Independent
Classifier: Programming Language :: Python
Classifier: Programming Language :: Python :: 3
Classifier: Programming Language :: Python :: 3 :: Only
Classifier: Programming Language :: Python :: 3.10
Classifier: Programming Language :: Python :: 3.11
Classifier: Programming Language :: Python :: 3.12
Classifier: Programming Language :: Python :: 3.13
Classifier: Programming Language :: Python :: Implementation :: CPython
Requires-Python: >=3.10
Requires-Dist: cachetools>=5.5.0
Requires-Dist: django-typer[rich]>=2.4.0
Requires-Dist: django>=4.2
Requires-Dist: gidgethub>=5.3.0
Requires-Dist: httpx>=0.27.2
